Simon-0.7.0.dist-info/DESCRIPTION.rst
Simon-0.7.0.dist-info/METADATA
Simon-0.7.0.dist-info/pydist.json
Simon-0.7.0.dist-info/RECORD
Simon-0.7.0.dist-info/top_level.txt
Simon-0.7.0.dist-info/WHEEL
usr/local/lib/python3.3/site-packages/simon/__init__.py
usr/local/lib/python3.3/site-packages/simon/_compat.py
usr/local/lib/python3.3/site-packages/simon/base.py
usr/local/lib/python3.3/site-packages/simon/connection.py
usr/local/lib/python3.3/site-packages/simon/exceptions.py
usr/local/lib/python3.3/site-packages/simon/geo.py
usr/local/lib/python3.3/site-packages/simon/meta.py
usr/local/lib/python3.3/site-packages/simon/query.py
usr/local/lib/python3.3/site-packages/simon/utils.py
