Metadata-Version: 1.1
Name: Simon
Version: 0.7.0
Summary: Simple MongoDB Models
Home-page: https://github.com/dirn/Simon
Author: Andy Dirnberger
Author-email: dirn@dirnonline.com
License: Copyright (c) 2013, Andy Dirnberger
